gradio/__init__.py
gradio/blocks.py
gradio/components.py
gradio/context.py
gradio/deprecation.py
gradio/documentation.py
gradio/encryptor.py
gradio/events.py
gradio/examples.py
gradio/external.py
gradio/flagging.py
gradio/inputs.py
gradio/interface.py
gradio/interpretation.py
gradio/ipython_ext.py
gradio/layouts.py
gradio/media_data.py
gradio/mix.py
gradio/networking.py
gradio/outputs.py
gradio/processing_utils.py
gradio/queueing.py
gradio/reload.py
gradio/routes.py
gradio/strings.py
gradio/templates.py
gradio/tunneling.py
gradio/utils.py
gradio/version.txt
gradio/templates/cdn/favicon.png
gradio/templates/cdn/gradio.js
gradio/templates/cdn/index.html
gradio/templates/cdn/assets/Block.ec6723bc.js
gradio/templates/cdn/assets/BlockLabel.910d3a12.js
gradio/templates/cdn/assets/BlockTitle.f3203dc4.js
gradio/templates/cdn/assets/CarouselItem.svelte_svelte_type_style_lang.1dcb2193.js
gradio/templates/cdn/assets/CarouselItem.svelte_svelte_type_style_lang.d8150608.css
gradio/templates/cdn/assets/File.a84fad2f.js
gradio/templates/cdn/assets/Image.57e1f8fd.js
gradio/templates/cdn/assets/Image.f41ada46.js
gradio/templates/cdn/assets/Model3D.b5239ffb.js
gradio/templates/cdn/assets/ModifyUpload.ebcd8f27.js
gradio/templates/cdn/assets/Tabs.d1d437b4.js
gradio/templates/cdn/assets/Upload.7df50210.js
gradio/templates/cdn/assets/Webcam.ac42cc12.js
gradio/templates/cdn/assets/_commonjsHelpers.88e99c8f.js
gradio/templates/cdn/assets/color.a9ac1f04.js
gradio/templates/cdn/assets/dsv.7fe76a93.js
gradio/templates/cdn/assets/index.06daef15.css
gradio/templates/cdn/assets/index.0862fcea.js
gradio/templates/cdn/assets/index.08ddd5ef.js
gradio/templates/cdn/assets/index.172d1c82.js
gradio/templates/cdn/assets/index.19bb94ff.css
gradio/templates/cdn/assets/index.1c55e62b.js
gradio/templates/cdn/assets/index.3263c87f.js
gradio/templates/cdn/assets/index.36895e8f.js
gradio/templates/cdn/assets/index.3f9ec57e.js
gradio/templates/cdn/assets/index.4424fa1a.js
gr_freddy-3.0.28.dev0.dist-info/LICENSE
gr_freddy-3.0.28.dev0.dist-info/METADATA
gr_freddy-3.0.28.dev0.dist-info/WHEEL
gr_freddy-3.0.28.dev0.dist-info/entry_points.txt
gr_freddy-3.0.28.dev0.dist-info/top_level.txt
gr_freddy-3.0.28.dev0.dist-info/RECORD
