Metadata-Version: 2.1
Name: gr-freddy
Version: 3.0.28.dev0
Summary: Python library for easily interacting with trained machine learning models
Home-page: https://github.com/gradio-app/gradio
Author: Abubakar Abid, Ali Abid, Ali Abdalla, Dawood Khan, Ahsen Khaliq, Pete Allen, Ömer Faruk Özdemir
Author-email: team@gradio.app
License: Apache License 2.0
Keywords: machine learning,visualization,reproducibility
Platform: UNKNOWN
Requires-Python: >=3.7
License-File: LICENSE
Requires-Dist: analytics-python
Requires-Dist: aiohttp
Requires-Dist: h11 (<0.13,>=0.11)
Requires-Dist: fastapi
Requires-Dist: ffmpy
Requires-Dist: markdown-it-py[linkify,plugins]
Requires-Dist: matplotlib
Requires-Dist: numpy
Requires-Dist: orjson
Requires-Dist: pandas
Requires-Dist: paramiko
Requires-Dist: pillow
Requires-Dist: pycryptodome
Requires-Dist: python-multipart
Requires-Dist: pydub
Requires-Dist: requests
Requires-Dist: uvicorn
Requires-Dist: Jinja2
Requires-Dist: fsspec
Requires-Dist: httpx
Requires-Dist: pydantic
